m2lk/__init__.py
m2lk/common.py
m2lk/m2.py
m2lk/skin.py
m2lk/structures.py
m2lk/utils.py
m2lk/vars.py
m2lk-0.0.2.dist-info/LICENSE
m2lk-0.0.2.dist-info/METADATA
m2lk-0.0.2.dist-info/WHEEL
m2lk-0.0.2.dist-info/top_level.txt
m2lk-0.0.2.dist-info/RECORD
