Metadata-Version: 2.1
Name: m2lk
Version: 0.0.2
Summary: WotLK M2 files parser
Home-page: https://github.com/Vladimir007/m2lk
Author: Vladimir Gratinskii
Author-email: vovangrat@gmail.com
License: UNKNOWN
Project-URL: Bug Tracker, https://github.com/Vladimir007/m2lk/issues
Platform: UNKNOWN
Classifier: Programming Language :: Python :: 3
Classifier: License :: OSI Approved :: MIT License
Classifier: Operating System :: OS Independent
Requires-Python: >=3.6
License-File: LICENSE
